kyew
